{
  "path_elements": [
    {
      "type": "waypoint",
      "translation_target": {
        "x_meters": 3.6899431228792707,
        "y_meters": 5.6450065714299935,
        "intermediate_handoff_radius_meters": 0.2
      },
      "rotation_target": {
        "rotation_radians": -0.01091532108175312,
        "profiled_rotation": true
      }
    },
    {
      "type": "event_trigger",
      "t_ratio": 0.3315249120361897,
      "lib_key": "IntakeAuto"
    },
    {
      "type": "waypoint",
      "translation_target": {
        "x_meters": 5.636746712723218,
        "y_meters": 5.649699191435708,
        "intermediate_handoff_radius_meters": 0.5499999999999998
      },
      "rotation_target": {
        "rotation_radians": 0.016772608802178558,
        "profiled_rotation": true
      }
    },
    {
      "type": "translation",
      "x_meters": 6.257024815014566,
      "y_meters": 6.671499785522175,
      "intermediate_handoff_radius_meters": 0.5499999999999999
    },
    {
      "type": "translation",
      "x_meters": 7.09623530173671,
      "y_meters": 7.3030771035979924,
      "intermediate_handoff_radius_meters": 0.39999999999999997
    },
    {
      "type": "waypoint",
      "translation_target": {
        "x_meters": 7.900166410259422,
        "y_meters": 7.290497823562316,
        "intermediate_handoff_radius_meters": 0.39999999999999997
      },
      "rotation_target": {
        "rotation_radians": -1.8935807493168788,
        "profiled_rotation": true
      }
    },
    {
      "type": "waypoint",
      "translation_target": {
        "x_meters": 7.903470734566488,
        "y_meters": 4.7938746062428645,
        "intermediate_handoff_radius_meters": 0.2
      },
      "rotation_target": {
        "rotation_radians": -2.0609486637192393,
        "profiled_rotation": true
      }
    },
    {
      "type": "waypoint",
      "translation_target": {
        "x_meters": 6.93711916656993,
        "y_meters": 4.678597652677891,
        "intermediate_handoff_radius_meters": 0.49999999999999994
      },
      "rotation_target": {
        "rotation_radians": 2.731425995617711,
        "profiled_rotation": false
      }
    },
    {
      "type": "event_trigger",
      "t_ratio": 0.0,
      "lib_key": "SpinUp"
    },
    {
      "type": "event_trigger",
      "t_ratio": 0.1314382624234421,
      "lib_key": "DefaultAuto"
    },
    {
      "type": "event_trigger",
      "t_ratio": 0.2931671524666204,
      "lib_key": "RaiseIntake"
    },
    {
      "type": "waypoint",
      "translation_target": {
        "x_meters": 5.889814029513421,
        "y_meters": 5.322307784327355,
        "intermediate_handoff_radius_meters": 0.2
      },
      "rotation_target": {
        "rotation_radians": -0.006388637804467051,
        "profiled_rotation": true
      }
    },
    {
      "type": "waypoint",
      "translation_target": {
        "x_meters": 3.4580718858426955,
        "y_meters": 5.349776870315365,
        "intermediate_handoff_radius_meters": 0.2
      },
      "rotation_target": {
        "rotation_radians": 0.0008541491007840785,
        "profiled_rotation": true
      }
    },
    {
      "type": "event_trigger",
      "t_ratio": 0.0,
      "lib_key": "DefaultAuto"
    },
    {
      "type": "event_trigger",
      "t_ratio": 0.8950651439409363,
      "lib_key": "Shoot"
    },
    {
      "type": "waypoint",
      "translation_target": {
        "x_meters": 3.0551096057050926,
        "y_meters": 5.542108939315857,
        "intermediate_handoff_radius_meters": 0.2
      },
      "rotation_target": {
        "rotation_radians": 2.254675289638213,
        "profiled_rotation": false
      }
    }
  ],
  "constraints": {
    "max_velocity_meters_per_sec": [
      {
        "value": 2.25,
        "start_ordinal": 7,
        "end_ordinal": 9
      },
      {
        "value": 1.5,
        "start_ordinal": 5,
        "end_ordinal": 5
      },
      {
        "value": 3.0,
        "start_ordinal": 3,
        "end_ordinal": 3
      },
      {
        "value": 2.0,
        "start_ordinal": 4,
        "end_ordinal": 4
      },
      {
        "value": 2.5,
        "start_ordinal": 1,
        "end_ordinal": 1
      }
    ]
  }
}